{
  "artist": {
    "id": 1655,
    "count": 1,
    "description": "Old Dominion is a modern American country music band",
    "link": "https://sub.music8.jp/category/old-dominion/",
    "name": "Old Dominion",
    "slug": "old-dominion",
    "taxonomy": "category",
    "parent": 0,
    "meta": [],
    "acf": {
      "artistorigin": "US",
      "artistactiveyearstart": "2007",
      "artistborn": "",
      "artistdied": "",
      "artistjpname": "オールド・ドミニオン",
      "member": false,
      "artistimage1": false,
      "Occupation": [
        {
          "value": "band",
          "label": "Band"
        }
      ]
    },
    "the_prefix": "",
    "_links": {
      "self": [
        {
          "href": "https://sub.music8.jp/wp-json/wp/v2/categories/1655",
          "targetHints": {
            "allow": [
              "GET"
            ]
          }
        }
      ],
      "collection": [
        {
          "href": "https://sub.music8.jp/wp-json/wp/v2/categories"
        }
      ],
      "about": [
        {
          "href": "https://sub.music8.jp/wp-json/wp/v2/taxonomies/category"
        }
      ],
      "wp:post_type": [
        {
          "href": "https://sub.music8.jp/wp-json/wp/v2/posts?categories=1655"
        },
        {
          "href": "https://sub.music8.jp/wp-json/wp/v2/playlist?categories=1655"
        }
      ],
      "curies": [
        {
          "name": "wp",
          "href": "https://api.w.org/{rel}",
          "templated": true
        }
      ]
    }
  },
  "songs": [
    {
      "id": 42111,
      "date": "2019-06-17T13:55:00",
      "date_gmt": "2019-06-17T04:55:00",
      "title": {
        "rendered": "One Man Band"
      },
      "content": {
        "rendered": "\n<p>OldDominion-OneManBand</p>\n",
        "protected": false
      },
      "categories": [
        1655
      ],
      "tags": [],
      "genre": [
        465
      ],
      "vocal": [
        2866
      ],
      "style": [
        2844
      ],
      "acf": {
        "likecount": "0",
        "artist_order": null,
        "spotify_track_id": "7cA3PnUQDlUyBBwpRozQeo",
        "spotify_release_date": "2019/10/25",
        "spotify_name": "One Man Band",
        "spotify_artists": "Old Dominion",
        "spotify_album": "Old Dominion",
        "spotify_images": "https://i.scdn.co/image/ab67616d0000b2735d76d260bbb9e3e5abe08bc2",
        "spotify_duration_ms": "186240",
        "spotify_popularity": "79",
        "spotify_danceability": "0.706",
        "spotify_energy": "0.358",
        "spotify_key": "6",
        "spotify_loudness": "-8.331",
        "spotify_mode": "1",
        "spotify_speechiness": "0.0347",
        "spotify_tempo": "75.991",
        "spotify_valence": "0.478",
        "spotify_acousticness": "0.677",
        "spotify_instrumentalness": "0",
        "spotify_time_signature": "4",
        "spotify_liveness": "0.107",
        "spotify_artists01": "Old Dominion",
        "spotify_artists01_id": "6y8XlgIV8BLlIg1tT1R10i",
        "spotify_artists01_images": "https://i.scdn.co/image/ab6761610000e5eb419f4ed09891d23992824466",
        "spotify_artists01_genres": "contemporary country, country, country road, modern country rock",
        "spotify_artists01_popularity": "69",
        "spotify_artists02": "",
        "spotify_artists02_id": "",
        "spotify_artists02_images": "",
        "spotify_artists02_genres": "",
        "spotify_artists02_popularity": "",
        "spotify_artists03": "",
        "spotify_artists03_id": "",
        "spotify_artists03_images": "",
        "spotify_artists03_genres": "",
        "spotify_artists03_popularity": "",
        "spotify_artists04": "",
        "spotify_artists04_id": "",
        "spotify_artists04_images": "",
        "spotify_artists04_genres": "",
        "spotify_artists04_popularitys": null,
        "potify_artists05": null,
        "spotify_artists05_id": "",
        "spotify_artists05_images": "",
        "spotify_artists05_genres": "",
        "spotify_artists05_popularity": "",
        "ytvideoid": "0lxA1FXOiv0",
        "ytreleasedate": null,
        "pvstyle": null
      },
      "featured_media_url": "https://sub.music8.jp/wp-content/uploads/Old-Dominion-One-Man-Band.jpg",
      "custom_fields": {
        "categories": [
          {
            "id": 1655,
            "name": "Old Dominion",
            "slug": "old-dominion",
            "acf": {
              "artistorigin": "US",
              "artistactiveyearstart": "2007",
              "artistborn": "",
              "artistdied": "",
              "artistjpname": "オールド・ドミニオン",
              "member": false,
              "artistimage1": false,
              "Occupation": [
                {
                  "value": "band",
                  "label": "Band"
                }
              ]
            },
            "artist_origin": null,
            "prefix": ""
          }
        ],
        "artist_order": null,
        "spotify_artists": "Old Dominion",
        "ytvideoid": "0lxA1FXOiv0",
        "spotify_track_id": "7cA3PnUQDlUyBBwpRozQeo"
      },
      "genre_data": [
        {
          "name": "Country",
          "slug": "country",
          "term_id": 465,
          "post_count": 123
        }
      ],
      "vocal_data": [
        {
          "name": "M",
          "slug": "male",
          "term_id": 2866
        }
      ],
      "slug": "one-man-band"
    }
  ],
  "totalSongs": 1,
  "totalPages": 1,
  "currentPage": 1
}