{
  "id": 87406,
  "title": "Another World (Kevin De Vries &#038; SLVR remix)",
  "artists": [
    {
      "id": 2123,
      "name": "Hayla",
      "slug": "hayla",
      "acf": {
        "artistorigin": "UK",
        "artistactiveyearstart": "",
        "artistborn": "",
        "artistdied": "",
        "artistjpname": "",
        "member": false,
        "artistimage1": false,
        "Occupation": [
          {
            "value": "singer",
            "label": "Singer"
          }
        ],
        "related_artists": "",
        "spotify_artist_id": "",
        "spotify_artist_images": ""
      },
      "artist_origin": null,
      "prefix": ""
    },
    {
      "id": 6296,
      "name": "Kevin De Vries",
      "slug": "kevin-de-vries",
      "acf": {
        "artistorigin": "GER",
        "artistactiveyearstart": "",
        "artistborn": "",
        "artistjpname": "",
        "member": false,
        "artistimage1": false,
        "artistdied": "",
        "Occupation": [],
        "related_artists": "",
        "spotify_artist_id": "11aPF3sc8lDWNqPVInm4Zx",
        "spotify_artist_images": "https://i.scdn.co/image/ab67616100005174fca0470ef4050a23e8be83a2"
      },
      "artist_origin": null,
      "prefix": ""
    },
    {
      "id": 1630,
      "name": "Meduza",
      "slug": "meduza",
      "acf": {
        "artistorigin": "ITA",
        "artistactiveyearstart": "2018",
        "artistborn": "",
        "artistdied": "",
        "artistjpname": "メドゥーザ",
        "member": false,
        "artistimage1": false
      },
      "artist_origin": null,
      "prefix": ""
    },
    {
      "id": 6297,
      "name": "SLVR",
      "slug": "slvr",
      "acf": {
        "artistorigin": "ITA",
        "artistactiveyearstart": "",
        "artistborn": "",
        "artistjpname": "",
        "member": false,
        "artistimage1": false,
        "artistdied": "",
        "Occupation": [],
        "related_artists": "",
        "spotify_artist_id": "4nKvbonPefiFmshjpHENVU",
        "spotify_artist_images": "https://i.scdn.co/image/ab67616100005174a825bf1a7bdc512d624d30e6"
      },
      "artist_origin": null,
      "prefix": ""
    }
  ],
  "genres": [
    {
      "name": "Progressive house",
      "slug": "progressive-house",
      "term_id": 670,
      "post_count": 240
    },
    {
      "name": "Vocal Trance",
      "slug": "vocal-trance",
      "term_id": 5573,
      "post_count": 10
    }
  ],
  "vocals": [
    {
      "name": "F",
      "slug": "female",
      "term_id": 2851
    }
  ],
  "releaseDate": "2024-11-15T18:05:32",
  "styles": [
    2846
  ],
  "thumbnail": "https://sub.music8.jp/wp-content/uploads/meduza-hayla-another-world-kevin-de-vries-slvr-remix.jpg",
  "videoId": "3epcQuRmKK4",
  "spotifyTrackId": "70hIxHhQLcxmqwxfcYkoUf",
  "appleMusicTrackId": "",
  "slug": "another-world-2",
  "custom_fields": {
    "categories": [
      {
        "id": 2123,
        "name": "Hayla",
        "slug": "hayla",
        "acf": {
          "artistorigin": "UK",
          "artistactiveyearstart": "",
          "artistborn": "",
          "artistdied": "",
          "artistjpname": "",
          "member": false,
          "artistimage1": false,
          "Occupation": [
            {
              "value": "singer",
              "label": "Singer"
            }
          ],
          "related_artists": "",
          "spotify_artist_id": "",
          "spotify_artist_images": ""
        },
        "artist_origin": null,
        "prefix": ""
      },
      {
        "id": 6296,
        "name": "Kevin De Vries",
        "slug": "kevin-de-vries",
        "acf": {
          "artistorigin": "GER",
          "artistactiveyearstart": "",
          "artistborn": "",
          "artistjpname": "",
          "member": false,
          "artistimage1": false,
          "artistdied": "",
          "Occupation": [],
          "related_artists": "",
          "spotify_artist_id": "11aPF3sc8lDWNqPVInm4Zx",
          "spotify_artist_images": "https://i.scdn.co/image/ab67616100005174fca0470ef4050a23e8be83a2"
        },
        "artist_origin": null,
        "prefix": ""
      },
      {
        "id": 1630,
        "name": "Meduza",
        "slug": "meduza",
        "acf": {
          "artistorigin": "ITA",
          "artistactiveyearstart": "2018",
          "artistborn": "",
          "artistdied": "",
          "artistjpname": "メドゥーザ",
          "member": false,
          "artistimage1": false
        },
        "artist_origin": null,
        "prefix": ""
      },
      {
        "id": 6297,
        "name": "SLVR",
        "slug": "slvr",
        "acf": {
          "artistorigin": "ITA",
          "artistactiveyearstart": "",
          "artistborn": "",
          "artistjpname": "",
          "member": false,
          "artistimage1": false,
          "artistdied": "",
          "Occupation": [],
          "related_artists": "",
          "spotify_artist_id": "4nKvbonPefiFmshjpHENVU",
          "spotify_artist_images": "https://i.scdn.co/image/ab67616100005174a825bf1a7bdc512d624d30e6"
        },
        "artist_origin": null,
        "prefix": ""
      }
    ],
    "artist_order": "",
    "spotify_artists": "MEDUZA, HAYLA, Kevin de Vries, SLVR",
    "ytvideoid": "3epcQuRmKK4",
    "spotify_track_id": "70hIxHhQLcxmqwxfcYkoUf"
  },
  "spotify_images": "https://i.scdn.co/image/ab67616d0000b273ef3480cc6ee58d4ac0b65c92",
  "content": "<p>MEDUZA, HAYLA - Another World (Kevin De Vries & SLVR remix)</p>\n",
  "modified": "2024-12-14T18:08:15",
  "lastUpdated": "2025-06-16T00:00:37.572Z",
  "acf": {
    "likecount": "1",
    "artist_order": "",
    "spotify_track_id": "70hIxHhQLcxmqwxfcYkoUf",
    "spotify_release_date": "2024-11-15",
    "spotify_name": "Another World - Kevin de Vries & SLVR Remix",
    "spotify_artists": "MEDUZA, HAYLA, Kevin de Vries, SLVR",
    "spotify_album": "Another World (Kevin de Vries & SLVR Remix)",
    "spotify_images": "https://i.scdn.co/image/ab67616d0000b273ef3480cc6ee58d4ac0b65c92",
    "spotify_duration_ms": "211653",
    "spotify_popularity": "57",
    "spotify_danceability": "undefined",
    "spotify_energy": "undefined",
    "spotify_key": "undefined",
    "spotify_loudness": "undefined",
    "spotify_mode": "undefined",
    "spotify_speechiness": "undefined",
    "spotify_tempo": "undefined",
    "spotify_valence": "undefined",
    "spotify_acousticness": "undefined",
    "spotify_instrumentalness": "undefined",
    "spotify_time_signature": "undefined",
    "spotify_liveness": "undefined",
    "spotify_artists01": "MEDUZA",
    "spotify_artists01_id": "0xRXCcSX89eobfrshSVdyu",
    "spotify_artists01_images": "https://i.scdn.co/image/ab6761610000e5eb4c49dba58421b29648964acd",
    "spotify_artists01_genres": "edm, pop dance, pop house, uk dance",
    "spotify_artists01_popularity": "75",
    "spotify_artists02": "HAYLA",
    "spotify_artists02_id": "4yX6mpMyBGf9UfvBB8JJrc",
    "spotify_artists02_images": "https://i.scdn.co/image/ab6761610000e5eb327e391ef0e0e7b11e2db1c9",
    "spotify_artists02_genres": "",
    "spotify_artists02_popularity": "69",
    "spotify_artists03": "Kevin de Vries",
    "spotify_artists03_id": "11aPF3sc8lDWNqPVInm4Zx",
    "spotify_artists03_images": "https://i.scdn.co/image/ab6761610000e5ebfca0470ef4050a23e8be83a2",
    "spotify_artists03_genres": "dark techno",
    "spotify_artists03_popularity": "57",
    "spotify_artists04": "SLVR",
    "spotify_artists04_id": "4nKvbonPefiFmshjpHENVU",
    "spotify_artists04_images": "https://i.scdn.co/image/ab6761610000e5eba825bf1a7bdc512d624d30e6",
    "spotify_artists04_genres": "bass house, big room",
    "spotify_artists04_popularitys": "49",
    "potify_artists05": "",
    "spotify_artists05_id": "",
    "spotify_artists05_images": "",
    "spotify_artists05_genres": "",
    "spotify_artists05_popularity": "",
    "ytvideoid": "3epcQuRmKK4",
    "ytreleasedate": "2024/11/15"
  }
}