{
  "id": 42495,
  "title": "California Friends",
  "artists": [
    {
      "id": 1251,
      "name": "Regrettes",
      "slug": "regrettes",
      "acf": {
        "artistorigin": "US",
        "artistactiveyearstart": "2015",
        "artistborn": "",
        "artistdied": "",
        "artistjpname": "ザ・リグレッツ",
        "member": false,
        "artistimage1": false,
        "Occupation": [
          {
            "value": "band",
            "label": "Band"
          }
        ]
      },
      "artist_origin": null,
      "prefix": ""
    }
  ],
  "genres": [
    {
      "name": "Garage rock",
      "slug": "garage-rock",
      "term_id": 536,
      "post_count": 59
    }
  ],
  "vocals": [
    {
      "name": "F",
      "slug": "female",
      "term_id": 2851
    }
  ],
  "releaseDate": "2018-10-05T17:03:00",
  "styles": [
    2844
  ],
  "thumbnail": "https://sub.music8.jp/wp-content/uploads/The-Regrettes-California-Friends.webp",
  "videoId": "FoX8YjQCR5I",
  "spotifyTrackId": "1KgS3NtxZ0yCVvWWHhYtyx",
  "appleMusicTrackId": "",
  "slug": "california-friends",
  "custom_fields": {
    "categories": [
      {
        "id": 1251,
        "name": "Regrettes",
        "slug": "regrettes",
        "acf": {
          "artistorigin": "US",
          "artistactiveyearstart": "2015",
          "artistborn": "",
          "artistdied": "",
          "artistjpname": "ザ・リグレッツ",
          "member": false,
          "artistimage1": false,
          "Occupation": [
            {
              "value": "band",
              "label": "Band"
            }
          ]
        },
        "artist_origin": null,
        "prefix": ""
      }
    ],
    "artist_order": null,
    "spotify_artists": "The Regrettes",
    "ytvideoid": "FoX8YjQCR5I",
    "spotify_track_id": "1KgS3NtxZ0yCVvWWHhYtyx"
  },
  "spotify_images": "https://i.scdn.co/image/ab67616d0000b273755fae5fd0ab091614b05b6b",
  "content": "\n<p>TheRegrettes-CaliforniaFriends</p>\n",
  "modified": "2018-10-05T17:03:00",
  "lastUpdated": "2025-06-16T00:00:50.674Z",
  "acf": {
    "likecount": "1",
    "artist_order": null,
    "spotify_track_id": "1KgS3NtxZ0yCVvWWHhYtyx",
    "spotify_release_date": "2019/8/9",
    "spotify_name": "California Friends",
    "spotify_artists": "The Regrettes",
    "spotify_album": "How Do You Love?",
    "spotify_images": "https://i.scdn.co/image/ab67616d0000b273755fae5fd0ab091614b05b6b",
    "spotify_duration_ms": "214186",
    "spotify_popularity": "46",
    "spotify_danceability": "0.601",
    "spotify_energy": "0.648",
    "spotify_key": "9",
    "spotify_loudness": "-5.495",
    "spotify_mode": "1",
    "spotify_speechiness": "0.0967",
    "spotify_tempo": "167.91",
    "spotify_valence": "0.393",
    "spotify_acousticness": "0.00398",
    "spotify_instrumentalness": "0",
    "spotify_time_signature": "4",
    "spotify_liveness": "0.177",
    "spotify_artists01": "The Regrettes",
    "spotify_artists01_id": "67WNUxmM7y4WzHPAVzBu3E",
    "spotify_artists01_images": "https://i.scdn.co/image/ab6761610000e5eb9ebec997f078b9a22b9a8356",
    "spotify_artists01_genres": "indie pop, la indie, pov: indie",
    "spotify_artists01_popularity": "48",
    "spotify_artists02": "",
    "spotify_artists02_id": "",
    "spotify_artists02_images": "",
    "spotify_artists02_genres": "",
    "spotify_artists02_popularity": "",
    "spotify_artists03": "",
    "spotify_artists03_id": "",
    "spotify_artists03_images": "",
    "spotify_artists03_genres": "",
    "spotify_artists03_popularity": "",
    "spotify_artists04": "",
    "spotify_artists04_id": "",
    "spotify_artists04_images": "",
    "spotify_artists04_genres": "",
    "spotify_artists04_popularitys": null,
    "potify_artists05": null,
    "spotify_artists05_id": "",
    "spotify_artists05_images": "",
    "spotify_artists05_genres": "",
    "spotify_artists05_popularity": "",
    "ytvideoid": "FoX8YjQCR5I",
    "ytreleasedate": null,
    "pvstyle": null
  }
}