{
  "artist": {
    "id": 3492,
    "count": 2,
    "description": "Shotgun Willy is an American rapper.",
    "link": "https://sub.music8.jp/category/shotgun-willy/",
    "name": "Shotgun Willy",
    "slug": "shotgun-willy",
    "taxonomy": "category",
    "parent": 0,
    "meta": [],
    "acf": {
      "artistorigin": "US",
      "artistactiveyearstart": "",
      "artistborn": "19990717",
      "artistjpname": "ショットガン・ウィリー",
      "member": false,
      "artistimage1": false,
      "artistdied": "",
      "Occupation": [
        {
          "value": "rapper",
          "label": "Rapper"
        }
      ]
    },
    "the_prefix": "",
    "_links": {
      "self": [
        {
          "href": "https://sub.music8.jp/wp-json/wp/v2/categories/3492",
          "targetHints": {
            "allow": [
              "GET"
            ]
          }
        }
      ],
      "collection": [
        {
          "href": "https://sub.music8.jp/wp-json/wp/v2/categories"
        }
      ],
      "about": [
        {
          "href": "https://sub.music8.jp/wp-json/wp/v2/taxonomies/category"
        }
      ],
      "wp:post_type": [
        {
          "href": "https://sub.music8.jp/wp-json/wp/v2/posts?categories=3492"
        },
        {
          "href": "https://sub.music8.jp/wp-json/wp/v2/playlist?categories=3492"
        }
      ],
      "curies": [
        {
          "name": "wp",
          "href": "https://api.w.org/{rel}",
          "templated": true
        }
      ]
    }
  },
  "songs": [
    {
      "id": 55797,
      "date": "2023-11-11T11:30:40",
      "date_gmt": "2023-11-11T02:30:40",
      "title": {
        "rendered": "Bombs Away"
      },
      "content": {
        "rendered": "<p>Shotgun Willy - Bombs Away</p>\n",
        "protected": false
      },
      "categories": [
        3492
      ],
      "tags": [],
      "genre": [
        657
      ],
      "vocal": [
        2866
      ],
      "style": [
        2844
      ],
      "acf": {
        "likecount": "1",
        "spotify_track_id": "6ihzpb4wOYkZut6iEC1MHE",
        "spotify_release_date": "2023-11-09",
        "spotify_name": "Bombs Away",
        "spotify_artists": "Shotgun Willy",
        "spotify_album": "Bombs Away",
        "spotify_images": "https://i.scdn.co/image/ab67616d0000b273619d7fd82e8de2c2ea9460e7",
        "spotify_duration_ms": "146000",
        "spotify_popularity": "48",
        "spotify_danceability": "0.76",
        "spotify_energy": "0.657",
        "spotify_key": "2",
        "spotify_loudness": "-5.632",
        "spotify_mode": "1",
        "spotify_speechiness": "0.134",
        "spotify_tempo": "99.999",
        "spotify_valence": "0.879",
        "spotify_acousticness": "0.171",
        "spotify_instrumentalness": "0",
        "spotify_time_signature": "4",
        "spotify_liveness": "0.0529",
        "spotify_artists01": "Shotgun Willy",
        "spotify_artists01_id": "7Gz6VlTVwlNtBNMYV4OI3w",
        "spotify_artists01_images": "https://i.scdn.co/image/ab6761610000e5ebd4638a34ab9f6af23f11e8c3",
        "spotify_artists01_genres": "meme rap",
        "spotify_artists01_popularity": "55",
        "spotify_artists02": "",
        "spotify_artists02_id": "",
        "spotify_artists02_images": "",
        "spotify_artists02_genres": "",
        "spotify_artists02_popularity": "",
        "spotify_artists03": "",
        "spotify_artists03_id": "",
        "spotify_artists03_images": "",
        "spotify_artists03_genres": "",
        "spotify_artists03_popularity": "",
        "spotify_artists04": "",
        "spotify_artists04_id": "",
        "spotify_artists04_images": "",
        "spotify_artists04_genres": "",
        "spotify_artists04_popularitys": "",
        "potify_artists05": "",
        "spotify_artists05_id": "",
        "spotify_artists05_images": "",
        "spotify_artists05_genres": "",
        "spotify_artists05_popularity": "",
        "ytvideoid": "F2GhFXjQujI",
        "ytreleasedate": "2023/11/11"
      },
      "featured_media_url": "https://sub.music8.jp/wp-content/uploads/Shotgun-Willy-Bombs-Away.webp",
      "custom_fields": {
        "categories": [
          {
            "id": 3492,
            "name": "Shotgun Willy",
            "slug": "shotgun-willy",
            "acf": {
              "artistorigin": "US",
              "artistactiveyearstart": "",
              "artistborn": "19990717",
              "artistjpname": "ショットガン・ウィリー",
              "member": false,
              "artistimage1": false,
              "artistdied": "",
              "Occupation": [
                {
                  "value": "rapper",
                  "label": "Rapper"
                }
              ]
            },
            "artist_origin": null,
            "prefix": ""
          }
        ],
        "artist_order": null,
        "spotify_artists": "Shotgun Willy",
        "ytvideoid": "F2GhFXjQujI",
        "spotify_track_id": "6ihzpb4wOYkZut6iEC1MHE"
      },
      "genre_data": [
        {
          "name": "Pop rap",
          "slug": "pop-rap",
          "term_id": 657,
          "post_count": 673
        }
      ],
      "vocal_data": [
        {
          "name": "M",
          "slug": "male",
          "term_id": 2866
        }
      ],
      "slug": "bombs-away-2"
    },
    {
      "id": 54670,
      "date": "2023-09-23T23:48:22",
      "date_gmt": "2023-09-23T14:48:22",
      "title": {
        "rendered": "Dalai Lama"
      },
      "content": {
        "rendered": "<p>Shotgun Willy - Dalai Lama</p>\n",
        "protected": false
      },
      "categories": [
        3492
      ],
      "tags": [],
      "genre": [
        657
      ],
      "vocal": [
        2866
      ],
      "style": [
        2844
      ],
      "acf": {
        "likecount": "1",
        "spotify_track_id": "3OXPEU3MLoJTWQmozs4IVc",
        "spotify_release_date": "2023-09-22",
        "spotify_name": "Dalai Lama",
        "spotify_artists": "Shotgun Willy",
        "spotify_album": "Dalai Lama",
        "spotify_images": "https://i.scdn.co/image/ab67616d0000b2735b986802a3a7d6cd0ce49a0c",
        "spotify_duration_ms": "135433",
        "spotify_popularity": "61",
        "spotify_danceability": "0.798",
        "spotify_energy": "0.833",
        "spotify_key": "4",
        "spotify_loudness": "-5.719",
        "spotify_mode": "0",
        "spotify_speechiness": "0.0461",
        "spotify_tempo": "149.994",
        "spotify_valence": "0.886",
        "spotify_acousticness": "0.188",
        "spotify_instrumentalness": "0.0000102",
        "spotify_time_signature": "4",
        "spotify_liveness": "0.407",
        "spotify_artists01": "Shotgun Willy",
        "spotify_artists01_id": "7Gz6VlTVwlNtBNMYV4OI3w",
        "spotify_artists01_images": "https://i.scdn.co/image/ab6761610000e5eb981f3b61db0ce8f5c70e8316",
        "spotify_artists01_genres": "meme rap",
        "spotify_artists01_popularity": "57",
        "spotify_artists02": "",
        "spotify_artists02_id": "",
        "spotify_artists02_images": "",
        "spotify_artists02_genres": "",
        "spotify_artists02_popularity": "",
        "spotify_artists03": "",
        "spotify_artists03_id": "",
        "spotify_artists03_images": "",
        "spotify_artists03_genres": "",
        "spotify_artists03_popularity": "",
        "spotify_artists04": "",
        "spotify_artists04_id": "",
        "spotify_artists04_images": "",
        "spotify_artists04_genres": "",
        "spotify_artists04_popularitys": "",
        "potify_artists05": "",
        "spotify_artists05_id": "",
        "spotify_artists05_images": "",
        "spotify_artists05_genres": "",
        "spotify_artists05_popularity": "",
        "ytvideoid": "r3npD8aCS9E",
        "ytreleasedate": "2023/09/23"
      },
      "featured_media_url": "https://sub.music8.jp/wp-content/uploads/Shotgun-Willy-Dalai-Lama.webp",
      "custom_fields": {
        "categories": [
          {
            "id": 3492,
            "name": "Shotgun Willy",
            "slug": "shotgun-willy",
            "acf": {
              "artistorigin": "US",
              "artistactiveyearstart": "",
              "artistborn": "19990717",
              "artistjpname": "ショットガン・ウィリー",
              "member": false,
              "artistimage1": false,
              "artistdied": "",
              "Occupation": [
                {
                  "value": "rapper",
                  "label": "Rapper"
                }
              ]
            },
            "artist_origin": null,
            "prefix": ""
          }
        ],
        "artist_order": null,
        "spotify_artists": "Shotgun Willy",
        "ytvideoid": "r3npD8aCS9E",
        "spotify_track_id": "3OXPEU3MLoJTWQmozs4IVc"
      },
      "genre_data": [
        {
          "name": "Pop rap",
          "slug": "pop-rap",
          "term_id": 657,
          "post_count": 673
        }
      ],
      "vocal_data": [
        {
          "name": "M",
          "slug": "male",
          "term_id": 2866
        }
      ],
      "slug": "dalai-lama"
    }
  ],
  "totalSongs": 2,
  "totalPages": 1,
  "currentPage": 1
}