{
  "artist": {
    "id": 3021,
    "count": 3,
    "description": "Jethro Tull are a British rock band.",
    "link": "https://sub.music8.jp/category/jethro-tull/",
    "name": "Jethro Tull",
    "slug": "jethro-tull",
    "taxonomy": "category",
    "parent": 0,
    "meta": [],
    "acf": {
      "artistorigin": "UK",
      "artistactiveyearstart": "1967",
      "artistborn": "",
      "artistdied": "",
      "artistjpname": "ジェスロ・タル",
      "member": [
        {
          "term_id": 768,
          "name": "Sting",
          "slug": "sting",
          "term_group": 0,
          "term_taxonomy_id": 768,
          "taxonomy": "category",
          "description": "Sting, is an English musician and actor. He was the frontman, songwriter and bassist for new wave band the Police.",
          "parent": 0,
          "count": 50,
          "filter": "raw"
        }
      ]
    },
    "the_prefix": "",
    "_links": {
      "self": [
        {
          "href": "https://sub.music8.jp/wp-json/wp/v2/categories/3021",
          "targetHints": {
            "allow": [
              "GET"
            ]
          }
        }
      ],
      "collection": [
        {
          "href": "https://sub.music8.jp/wp-json/wp/v2/categories"
        }
      ],
      "about": [
        {
          "href": "https://sub.music8.jp/wp-json/wp/v2/taxonomies/category"
        }
      ],
      "wp:post_type": [
        {
          "href": "https://sub.music8.jp/wp-json/wp/v2/posts?categories=3021"
        },
        {
          "href": "https://sub.music8.jp/wp-json/wp/v2/playlist?categories=3021"
        }
      ],
      "curies": [
        {
          "name": "wp",
          "href": "https://api.w.org/{rel}",
          "templated": true
        }
      ]
    }
  },
  "songs": [
    {
      "id": 90335,
      "date": "2025-02-06T21:32:50",
      "date_gmt": "2025-02-06T12:32:50",
      "title": {
        "rendered": "The Tipu House"
      },
      "content": {
        "rendered": "<p>Jethro Tull - The Tipu House</p>\n",
        "protected": false
      },
      "categories": [
        3021
      ],
      "tags": [],
      "genre": [
        519,
        6406
      ],
      "vocal": [
        2866
      ],
      "style": [
        2844
      ],
      "acf": {
        "ytvideoid": "LnAYn2Ff58E",
        "ytreleasedate": "2025/02/06",
        "pvstyle": [
          "pv"
        ],
        "likecount": "1",
        "artist_order": "",
        "spotify_track_id": "4H9PdXyyajRGJAV7bjtl9g",
        "spotify_release_date": "2025-02-06",
        "spotify_name": "The Tipu House",
        "spotify_artists": "ジェスロ・タル",
        "spotify_album": "The Tipu House",
        "spotify_images": "https://i.scdn.co/image/ab67616d0000b273444d6ea1e8621553db7b624d",
        "spotify_duration_ms": "211173",
        "spotify_popularity": "29",
        "spotify_danceability": "undefined",
        "spotify_energy": "undefined",
        "spotify_key": "undefined",
        "spotify_loudness": "undefined",
        "spotify_mode": "undefined",
        "spotify_speechiness": "undefined",
        "spotify_tempo": "undefined",
        "spotify_valence": "undefined",
        "spotify_acousticness": "undefined",
        "spotify_instrumentalness": "undefined",
        "spotify_time_signature": "undefined",
        "spotify_liveness": "undefined",
        "spotify_artists01": "ジェスロ・タル",
        "spotify_artists01_id": "6w6z8m4WXX7Tub4Rb6Lu7R",
        "spotify_artists01_images": "https://i.scdn.co/image/ab6761610000e5ebe1d4d487ce0407b9ecb96743",
        "spotify_artists01_genres": "プログレッシブロック, シンフォニック・ロック, アート・ロック, クラシックロック",
        "spotify_artists01_popularity": "56",
        "spotify_artists02": "",
        "spotify_artists02_id": "",
        "spotify_artists02_images": "",
        "spotify_artists02_genres": "",
        "spotify_artists02_popularity": "",
        "spotify_artists03": "",
        "spotify_artists03_id": "",
        "spotify_artists03_images": "",
        "spotify_artists03_genres": "",
        "spotify_artists03_popularity": "",
        "spotify_artists04": "",
        "spotify_artists04_id": "",
        "spotify_artists04_images": "",
        "spotify_artists04_genres": "",
        "spotify_artists04_popularitys": "",
        "potify_artists05": "",
        "spotify_artists05_id": "",
        "spotify_artists05_images": "",
        "spotify_artists05_genres": "",
        "spotify_artists05_popularity": ""
      },
      "featured_media_url": "https://sub.music8.jp/wp-content/uploads/jethro-tull-the-tipu-house.jpg",
      "custom_fields": {
        "categories": [
          {
            "id": 3021,
            "name": "Jethro Tull",
            "slug": "jethro-tull",
            "acf": {
              "artistorigin": "UK",
              "artistactiveyearstart": "1967",
              "artistborn": "",
              "artistdied": "",
              "artistjpname": "ジェスロ・タル",
              "member": [
                {
                  "term_id": 768,
                  "name": "Sting",
                  "slug": "sting",
                  "term_group": 0,
                  "term_taxonomy_id": 768,
                  "taxonomy": "category",
                  "description": "Sting, is an English musician and actor. He was the frontman, songwriter and bassist for new wave band the Police.",
                  "parent": 0,
                  "count": 50,
                  "filter": "raw"
                }
              ]
            },
            "artist_origin": null,
            "prefix": ""
          }
        ],
        "artist_order": "",
        "spotify_artists": "ジェスロ・タル",
        "ytvideoid": "LnAYn2Ff58E",
        "spotify_track_id": "4H9PdXyyajRGJAV7bjtl9g"
      },
      "genre_data": [
        {
          "name": "Folk rock",
          "slug": "folk-rock",
          "term_id": 519,
          "post_count": 97
        },
        {
          "name": "Progressive Folk",
          "slug": "progressive-folk",
          "term_id": 6406,
          "post_count": 4
        }
      ],
      "vocal_data": [
        {
          "name": "M",
          "slug": "male",
          "term_id": 2866
        }
      ],
      "slug": "the-tipu-house"
    },
    {
      "id": 89305,
      "date": "2025-01-10T11:12:40",
      "date_gmt": "2025-01-10T02:12:40",
      "title": {
        "rendered": "Curious Ruminant"
      },
      "content": {
        "rendered": "<p>Jethro Tull - Curious Ruminant</p>\n",
        "protected": false
      },
      "categories": [
        3021
      ],
      "tags": [],
      "genre": [
        6406,
        674
      ],
      "vocal": [
        2866
      ],
      "style": [
        2849
      ],
      "acf": {
        "ytvideoid": "sFOv9HHe19c",
        "ytreleasedate": "2025/01/10",
        "pvstyle": [
          "pv"
        ],
        "likecount": "1",
        "artist_order": "",
        "spotify_track_id": "1GwbwKkKsj3EqkJda5RdoR",
        "spotify_release_date": "2025-01-10",
        "spotify_name": "Curious Ruminant",
        "spotify_artists": "ジェスロ・タル",
        "spotify_album": "Curious Ruminant",
        "spotify_images": "https://i.scdn.co/image/ab67616d0000b2739a868ad9ccc0322ea1a890ff",
        "spotify_duration_ms": "360120",
        "spotify_popularity": "0",
        "spotify_danceability": "undefined",
        "spotify_energy": "undefined",
        "spotify_key": "undefined",
        "spotify_loudness": "undefined",
        "spotify_mode": "undefined",
        "spotify_speechiness": "undefined",
        "spotify_tempo": "undefined",
        "spotify_valence": "undefined",
        "spotify_acousticness": "undefined",
        "spotify_instrumentalness": "undefined",
        "spotify_time_signature": "undefined",
        "spotify_liveness": "undefined",
        "spotify_artists01": "ジェスロ・タル",
        "spotify_artists01_id": "6w6z8m4WXX7Tub4Rb6Lu7R",
        "spotify_artists01_images": "https://i.scdn.co/image/ab6761610000e5ebe1d4d487ce0407b9ecb96743",
        "spotify_artists01_genres": "album rock, art rock, blues rock, classic rock, flute rock, folk rock, hard rock, progressive rock, psychedelic rock, rock, singer-songwriter, symphonic rock",
        "spotify_artists01_popularity": "60",
        "spotify_artists02": "",
        "spotify_artists02_id": "",
        "spotify_artists02_images": "",
        "spotify_artists02_genres": "",
        "spotify_artists02_popularity": "",
        "spotify_artists03": "",
        "spotify_artists03_id": "",
        "spotify_artists03_images": "",
        "spotify_artists03_genres": "",
        "spotify_artists03_popularity": "",
        "spotify_artists04": "",
        "spotify_artists04_id": "",
        "spotify_artists04_images": "",
        "spotify_artists04_genres": "",
        "spotify_artists04_popularitys": "",
        "potify_artists05": "",
        "spotify_artists05_id": "",
        "spotify_artists05_images": "",
        "spotify_artists05_genres": "",
        "spotify_artists05_popularity": ""
      },
      "featured_media_url": "https://sub.music8.jp/wp-content/uploads/jethro-tull-curious-ruminant.jpg",
      "custom_fields": {
        "categories": [
          {
            "id": 3021,
            "name": "Jethro Tull",
            "slug": "jethro-tull",
            "acf": {
              "artistorigin": "UK",
              "artistactiveyearstart": "1967",
              "artistborn": "",
              "artistdied": "",
              "artistjpname": "ジェスロ・タル",
              "member": [
                {
                  "term_id": 768,
                  "name": "Sting",
                  "slug": "sting",
                  "term_group": 0,
                  "term_taxonomy_id": 768,
                  "taxonomy": "category",
                  "description": "Sting, is an English musician and actor. He was the frontman, songwriter and bassist for new wave band the Police.",
                  "parent": 0,
                  "count": 50,
                  "filter": "raw"
                }
              ]
            },
            "artist_origin": null,
            "prefix": ""
          }
        ],
        "artist_order": "",
        "spotify_artists": "ジェスロ・タル",
        "ytvideoid": "sFOv9HHe19c",
        "spotify_track_id": "1GwbwKkKsj3EqkJda5RdoR"
      },
      "genre_data": [
        {
          "name": "Progressive Folk",
          "slug": "progressive-folk",
          "term_id": 6406,
          "post_count": 4
        },
        {
          "name": "Progressive rock",
          "slug": "progressive-rock",
          "term_id": 674,
          "post_count": 48
        }
      ],
      "vocal_data": [
        {
          "name": "M",
          "slug": "male",
          "term_id": 2866
        }
      ],
      "slug": "curious-ruminant"
    },
    {
      "id": 50602,
      "date": "2023-02-22T14:41:00",
      "date_gmt": "2023-02-22T05:41:54",
      "title": {
        "rendered": "The Navigators"
      },
      "content": {
        "rendered": "<p>Jethro Tull – The Navigators</p>\n",
        "protected": false
      },
      "categories": [
        3021
      ],
      "tags": [],
      "genre": [
        519,
        674
      ],
      "vocal": [
        2866
      ],
      "style": [
        2845
      ],
      "acf": {
        "likecount": "1",
        "spotify_track_id": "1AXRMCtukyZt9PZ7lApQ2x",
        "spotify_release_date": "2023/4/21",
        "spotify_name": "The Navigators - Single Edit",
        "spotify_artists": "Jethro Tull",
        "spotify_album": "RökFlöte",
        "spotify_images": "https://i.scdn.co/image/ab67616d0000b273d417d2318dd32af808a5c9ea",
        "spotify_duration_ms": "204800",
        "spotify_popularity": "29",
        "spotify_danceability": "0.583",
        "spotify_energy": "0.765",
        "spotify_key": "5",
        "spotify_loudness": "-9.162",
        "spotify_mode": "1",
        "spotify_speechiness": "0.0372",
        "spotify_tempo": "123.969",
        "spotify_valence": "0.494",
        "spotify_acousticness": "0.0147",
        "spotify_instrumentalness": "0.000885",
        "spotify_time_signature": "4",
        "spotify_liveness": "0.0736",
        "spotify_artists01": "ジェスロ・タル",
        "spotify_artists01_id": "6w6z8m4WXX7Tub4Rb6Lu7R",
        "spotify_artists01_images": "https://i.scdn.co/image/ab6761610000e5ebb94631f08038eac322c090f0",
        "spotify_artists01_genres": "album rock, art rock, blues rock, classic rock, flute rock, folk rock, hard rock, progressive rock, psychedelic rock, rock, singer-songwriter, symphonic rock",
        "spotify_artists01_popularity": "57",
        "spotify_artists02": "",
        "spotify_artists02_id": "",
        "spotify_artists02_images": "",
        "spotify_artists02_genres": "",
        "spotify_artists02_popularity": "",
        "spotify_artists03": "",
        "spotify_artists03_id": "",
        "spotify_artists03_images": "",
        "spotify_artists03_genres": "",
        "spotify_artists03_popularity": "",
        "spotify_artists04": "",
        "spotify_artists04_id": "",
        "spotify_artists04_images": "",
        "spotify_artists04_genres": "",
        "spotify_artists04_popularitys": "",
        "potify_artists05": "",
        "spotify_artists05_id": "",
        "spotify_artists05_images": "",
        "spotify_artists05_genres": "",
        "spotify_artists05_popularity": "",
        "ytvideoid": "HUTtSU_6y1c",
        "ytreleasedate": "2023/2/22"
      },
      "featured_media_url": "https://sub.music8.jp/wp-content/uploads/Jethro-Tull-–-The-Navigators.webp",
      "custom_fields": {
        "categories": [
          {
            "id": 3021,
            "name": "Jethro Tull",
            "slug": "jethro-tull",
            "acf": {
              "artistorigin": "UK",
              "artistactiveyearstart": "1967",
              "artistborn": "",
              "artistdied": "",
              "artistjpname": "ジェスロ・タル",
              "member": [
                {
                  "term_id": 768,
                  "name": "Sting",
                  "slug": "sting",
                  "term_group": 0,
                  "term_taxonomy_id": 768,
                  "taxonomy": "category",
                  "description": "Sting, is an English musician and actor. He was the frontman, songwriter and bassist for new wave band the Police.",
                  "parent": 0,
                  "count": 50,
                  "filter": "raw"
                }
              ]
            },
            "artist_origin": null,
            "prefix": ""
          }
        ],
        "artist_order": null,
        "spotify_artists": "Jethro Tull",
        "ytvideoid": "HUTtSU_6y1c",
        "spotify_track_id": "1AXRMCtukyZt9PZ7lApQ2x"
      },
      "genre_data": [
        {
          "name": "Folk rock",
          "slug": "folk-rock",
          "term_id": 519,
          "post_count": 97
        },
        {
          "name": "Progressive rock",
          "slug": "progressive-rock",
          "term_id": 674,
          "post_count": 48
        }
      ],
      "vocal_data": [
        {
          "name": "M",
          "slug": "male",
          "term_id": 2866
        }
      ],
      "slug": "the-navigators"
    }
  ],
  "totalSongs": 3,
  "totalPages": 1,
  "currentPage": 1
}